uyuni_health_check/__init__.py
uyuni_health_check/config.py
uyuni_health_check/config.toml
uyuni_health_check/main.py
uyuni_health_check/utils.py
uyuni_health_check/config/grafana/alerts.yaml
uyuni_health_check/config/grafana/dashboard.yaml
uyuni_health_check/config/grafana/datasources.yaml
uyuni_health_check/config/grafana/dashboards/dashboard_with_logs.json
uyuni_health_check/config/loki/config.yaml
uyuni_health_check/config/prometheus/prometheus.yml
uyuni_health_check/config/templates/exporter/exporter.yaml.j2
uyuni_health_check/config/templates/grafana_dashboard/supportconfig_with_logs.template.json
uyuni_health_check/config/templates/promtail/promtail.yaml.j2
uyuni_health_check/containers/manager.py
uyuni_health_check/containers/exporter/Dockerfile
uyuni_health_check/containers/exporter/requirements.txt
uyuni_health_check/containers/grafana/Containerfile
uyuni_health_check/containers/loki/Dockerfile
uyuni_health_check/containers/promtail/Dockerfile
uyuni_health_check/containers/promtail/complete_checker.py
uyuni_health_check/containers/promtail/run.py
uyuni_health_check/exporters/exporter.py
uyuni_health_check/exporters/static_metrics.py
uyuni_health_check/exporters/supportconfig_exporter.py
uyuni_health_check/grafana/grafana_manager.py
uyuni_health_check/loki/loki_manager.py
uyuni_health_check-0.0.1.dist-info/METADATA
uyuni_health_check-0.0.1.dist-info/WHEEL
uyuni_health_check-0.0.1.dist-info/entry_points.txt
uyuni_health_check-0.0.1.dist-info/top_level.txt
uyuni_health_check-0.0.1.dist-info/RECORD
