Metadata-Version: 2.2
Name: uyuni-health-check
Version: 0.0.1
Summary: Show Uyuni server health metrics and logs
Maintainer-email: Pablo Suárez Hernández <psuarezhernandez@suse.com>
Project-URL: homepage, https://github.com/uyuni-project/uyuni
Project-URL: tracker, https://github.com/uyuni-project/uyuni/issues
Classifier: Programming Language :: Python :: 3
Classifier: Operating System :: OS Independent
Requires-Python: >=3.11
Requires-Dist: Click
Requires-Dist: rich
Requires-Dist: requests
Requires-Dist: Jinja2
Requires-Dist: PyYAML
Requires-Dist: tomli
